HISTORY.md
LICENSE
MANIFEST.in
README.md
requirements.txt
setup.py
django_djconfig.egg-info/PKG-INFO
django_djconfig.egg-info/SOURCES.txt
django_djconfig.egg-info/dependency_links.txt
django_djconfig.egg-info/not-zip-safe
django_djconfig.egg-info/top_level.txt
djconfig/__init__.py
djconfig/admin.py
djconfig/apps.py
djconfig/conf.py
djconfig/context_processors.py
djconfig/forms.py
djconfig/middleware.py
djconfig/models.py
djconfig/utils.py
djconfig/migrations/0001_initial.py
djconfig/migrations/__init__.py
djconfig/templates/admin/djconfig/change_list.html